README.md
setup.cfg
setup.py
eiger_simulator.egg-info/PKG-INFO
eiger_simulator.egg-info/SOURCES.txt
eiger_simulator.egg-info/dependency_links.txt
eiger_simulator.egg-info/entry_points.txt
eiger_simulator.egg-info/requires.txt
eiger_simulator.egg-info/top_level.txt
eigersim/__init__.py
eigersim/acquisition.py
eigersim/client.py
eigersim/clz4.py
eigersim/config.py
eigersim/dataset.py
eigersim/server.py
eigersim/tool.py
eigersim/web.py
eigersim/static/js/jquery-3.5.1.slim.min.js
eigersim/templates/index.html