Metadata-Version: 2.1
Name: eiger-simulator
Version: 0.5.1
Summary: ALBA Eiger simulator
Home-page: https://git.cells.es/controls/eiger-simulator
Author: ALBA controls team
Author-email: controls@cells.es
License: GPL
Keywords: alba,dectris,eiger,simulator
Platform: UNKNOWN
Classifier: Development Status :: 2 - Pre-Alpha
Classifier: Intended Audience :: Developers
Classifier: Natural Language :: English
Classifier: Programming Language :: Python :: 3
Classifier: Programming Language :: Python :: 3.7
Classifier: Programming Language :: Python :: 3.8
Requires-Python: >=3.7
Provides-Extra: client
Provides-Extra: lima
